audioslicer/__init__.py
audioslicer/slicer.py
lm_audioslicer-0.1.8.dist-info/LICENSE
lm_audioslicer-0.1.8.dist-info/METADATA
lm_audioslicer-0.1.8.dist-info/WHEEL
lm_audioslicer-0.1.8.dist-info/entry_points.txt
lm_audioslicer-0.1.8.dist-info/top_level.txt
lm_audioslicer-0.1.8.dist-info/RECORD
