Metadata-Version: 2.1
Name: lm_audioslicer
Version: 0.1.8
Summary: Tool for slicing long audio files for datasets
Home-page: https://github.com/LarsMonstad/audioslicer
Author: Lars Monstad
Author-email: Lars Monstad <lars.monstad@gmail.com>
License: MIT License
Project-URL: Homepage, https://github.com/LarsMonstad/audioslicer
Project-URL: Issues, https://github.com/LarsMonstad/audioslicer/issues
Classifier: Programming Language :: Python :: 3
Classifier: Operating System :: OS Independent
Classifier: License :: OSI Approved :: MIT License
Requires-Python: >=3.8
License-File: LICENSE
Requires-Dist: librosa ==0.9.1
Requires-Dist: soundfile >=0.12.1
Requires-Dist: numpy ==1.23.5
